README.md
setup.py
jsonutils/__init__.py
jsonutils/json_object.py
jsonutils3.egg-info/PKG-INFO
jsonutils3.egg-info/SOURCES.txt
jsonutils3.egg-info/dependency_links.txt
jsonutils3.egg-info/top_level.txt