Metadata-Version: 2.1
Name: jsonutils3
Version: 1.0.0
Summary: A lib to use json easly.
Home-page: http://github.com/LavaPower/jsonutils
Author: LavaPower
Author-email: lavapower84@gmail.com
License: UNKNOWN
Platform: UNKNOWN
Classifier: Programming Language :: Python
Classifier: Development Status :: 1 - Planning
Classifier: License :: OSI Approved :: GNU General Public License v3 (GPLv3)
Classifier: Natural Language :: English
Classifier: Operating System :: OS Independent
Classifier: Programming Language :: Python :: 3.7
Classifier: Intended Audience :: Developers
